{"total_rows":245,"offset":0,"rows":[
{"id":"1","key":"1","value":"8_full.jpg"},
{"id":"10","key":"10","value":"ohsu-0058-5-OD-posterior2.bmp"},
{"id":"100","key":"100","value":"miam-0014-3-os.BMP"},
{"id":"101","key":"101","value":"24_Full.TIF"},
{"id":"102","key":"102","value":"ohsu-0041-am-1st-OS-posterior.bmp"},
{"id":"103","key":"103","value":"ohsu-0046-vv-1st-OS-posterior.bmp"},
{"id":"104","key":"104","value":"ohsu-0070-7-OS-posterior.bmp"},
{"id":"105","key":"105","value":"ohsu-0083-2-OD-posterior.bmp"},
{"id":"106","key":"106","value":"ohsu-0063-3-OS-posterior.bmp"},
{"id":"107","key":"107","value":"ohsu-0044-5-OS-posterior2.bmp"},
{"id":"108","key":"108","value":"miam-0018-5-od.BMP"},
{"id":"109","key":"109","value":"ohsu-0082-2-OS-posterior.bmp"},
{"id":"11","key":"11","value":"24-second-OS-posterior.bmp"},
{"id":"110","key":"110","value":"ohsu-0083-2-OS-posterior.bmp"},
{"id":"111","key":"111","value":"ohsu-0124-6-OS-posterior.bmp"},
{"id":"112","key":"112","value":"5_Full.JPG"},
{"id":"113","key":"113","value":"miam-0011-2-od.BMP"},
{"id":"114","key":"114","value":"ohsu-0065-1-OD-posterior.bmp"},
{"id":"115","key":"115","value":"ohsu-0058-hv-5-OD-posterior2.bmp"},
{"id":"116","key":"116","value":"ohsu-0010-cm-3rd session-OD-posterior2.bmp"},
{"id":"117","key":"117","value":"ohsu-0041-am-1st-OD-posterior.bmp"},
{"id":"118","key":"118","value":"ohsu-0054-4-os.bmp"},
{"id":"119","key":"119","value":"ohsu-0038-eh-1st-OD-posterior.bmp"},
{"id":"12","key":"12","value":"ohsu-0049-10-os.bmp"},
{"id":"120","key":"120","value":"ohsu-0034-8-od-posterior2.bmp"},
{"id":"121","key":"121","value":"ohsu-0046-vv-2nd-OD-posterior.bmp"},
{"id":"122","key":"122","value":"32_Full.JPG"},
{"id":"123","key":"123","value":"miam-0018-4-os.BMP"},
{"id":"124","key":"124","value":"ohsu-0017-nh-2nd-OD-posterior2.bmp"},
{"id":"125","key":"125","value":"ohsu-0001-6-os-posterior2.bmp"},
{"id":"126","key":"126","value":"corn-0018-3-od-posterior.bmp"},
{"id":"127","key":"127","value":"RCOL-0024-second-OD-posterior.bmp"},
{"id":"128","key":"128","value":"ohsu-0029-ps-2nd-OD-posterior.bmp"},
{"id":"129","key":"129","value":"ohsu-0039-xm-1st-OD-posterior.bmp"},
{"id":"13","key":"13","value":"ohsu-0001-6-OD-posterior.bmp"},
{"id":"130","key":"130","value":"33_Full.JPG"},
{"id":"131","key":"131","value":"ohsu-0060-3-OS-posterior.bmp"},
{"id":"132","key":"132","value":"ohsu-0049-10-os.bmp"},
{"id":"133","key":"133","value":"ohsu-0032-jv-3rd-OD-posterior.bmp"},
{"id":"134","key":"134","value":"ohsu-0002-2-od-posterior2.bmp"},
{"id":"135","key":"135","value":"ohsu-0065-1-OS-posterior.bmp"},
{"id":"136","key":"136","value":"ohsu-0008-jf-3rd session-OS-posterior2.bmp"},
{"id":"137","key":"137","value":"ohsu-0124-6-OD-posterior.bmp"},
{"id":"138","key":"138","value":"ohsu-0096-1-OS-posterior.bmp"},
{"id":"139","key":"139","value":"ohsu-0038-eh-2nd-OD-posterior.bmp"},
{"id":"14","key":"14","value":"rcor-0005-1-os-posterior.bmp"},
{"id":"140","key":"140","value":"ohsu-0057-5-os.bmp"},
{"id":"141","key":"141","value":"30_Full.bmp"},
{"id":"142","key":"142","value":"ohsu-0054-5-os.bmp"},
{"id":"143","key":"143","value":"ohsu-0049-nv-14-OS-posterior2.bmp"},
{"id":"144","key":"144","value":"ohsu-0079-3-OS-posterior.bmp"},
{"id":"145","key":"145","value":"corn-0018-3-os-posterior.bmp"},
{"id":"146","key":"146","value":"ohsu-0118-10-OD-posterior.bmp"},
{"id":"147","key":"147","value":"ohsu-0123-4-OS-posterior.bmp"},
{"id":"148","key":"148","value":"ohsu-0135-7-OS-posterior.bmp"},
{"id":"149","key":"149","value":"8_Full.JPG"},
{"id":"15","key":"15","value":"rcol-0024-2-OD-posterior.bmp"},
{"id":"150","key":"150","value":"ohsu-0020-gl-5th-OD-posterior.bmp"},
{"id":"151","key":"151","value":"ohsu-0015-cw-1st-OS-posterior.bmp"},
{"id":"152","key":"152","value":"miam-0001-2-os.BMP"},
{"id":"153","key":"153","value":"13_Full.JPG"},
{"id":"154","key":"154","value":"ohsu-0063-1-OS-posterior.bmp"},
{"id":"155","key":"155","value":"ohsu-0053-js-2nd-OS-posterior.bmp"},
{"id":"156","key":"156","value":"ohsu-0076-6-OD-posterior.bmp"},
{"id":"157","key":"157","value":"ohsu-0084-7-OS-posterior.bmp"},
{"id":"158","key":"158","value":"ohsu-0085-2-OD-posterior.bmp"},
{"id":"159","key":"159","value":"miam-0012-2-od.BMP"},
{"id":"16","key":"16","value":"ohsu-0109-1-OD-posterior.bmp"},
{"id":"160","key":"160","value":"ohsu-0011-mb-2nd-OS-posterior.bmp"},
{"id":"161","key":"161","value":"ohsu-0040-tm-1st-OD-posterior.bmp"},
{"id":"162","key":"162","value":"ohsu-001-gb-6th session-OD-posterior1.bmp"},
{"id":"163","key":"163","value":"ohsu-0002-3-os-posterior2.bmp"},
{"id":"164","key":"164","value":"miam--0027-2-od.BMP"},
{"id":"165","key":"165","value":"beau-0008-1-OS-posterior.bmp"},
{"id":"166","key":"166","value":"ohsu-0103-2-OS-posterior.bmp"},
{"id":"167","key":"167","value":"beau-0061-4-OS-posterior.bmp"},
{"id":"168","key":"168","value":"ohsu-0104-8-OS-posterior.bmp"},
{"id":"169","key":"169","value":"ohsu-0109-1-OD-posterior.bmp"},
{"id":"17","key":"17","value":"ohsu-0043-aw-6th-OS-posterior.bmp"},
{"id":"170","key":"170","value":"ohsu-0087-4-OS-posterior.bmp"},
{"id":"171","key":"171","value":"ohsu-0021-cl-2nd-OD-posterior.bmp"},
{"id":"172","key":"172","value":"corn-0025-2-os.bmp"},
{"id":"173","key":"173","value":"ohsu-0001-4-od-posterior2.bmp"},
{"id":"174","key":"174","value":"ohsu-0043-aw-6th-OS-posterior.bmp"},
{"id":"175","key":"175","value":"ohsu-0006-sr-2nd session-OS-posterior.bmp"},
{"id":"176","key":"176","value":"ohsu-0063-2-OD-posterior.bmp"},
{"id":"177","key":"177","value":"ohsu-0039-xm-2nd-OS-posterior.bmp"},
{"id":"178","key":"178","value":"ohsu-0072-2-OS-posterior.bmp"},
{"id":"179","key":"179","value":"ohsu-0072-2-OD-posterior.bmp"},
{"id":"18","key":"18","value":"ohsu-0006-2-OS-posterior.bmp"},
{"id":"180","key":"180","value":"ohsu-0058-hv-5-OS-posterior2.bmp"},
{"id":"181","key":"181","value":"RCOL-0024-second-OS-posterior.bmp"},
{"id":"182","key":"182","value":"4_Full.JPG"},
{"id":"183","key":"183","value":"ohsu-0117-1-OD-posterior.bmp"},
{"id":"184","key":"184","value":"ohsu-0030-ks-3rd-OS-posterior.bmp"},
{"id":"185","key":"185","value":"OHSU-0024-em-1st-OS-posterior.bmp"},
{"id":"186","key":"186","value":"ohsu-0058-5-OD-posterior.bmp"},
{"id":"187","key":"187","value":"24-second-OS-temporal.bmp"},
{"id":"188","key":"188","value":"ohsu-0073-2-OS-posterior.bmp"},
{"id":"189","key":"189","value":"ohsu-0073-1-OD-posterior.bmp"},
{"id":"19","key":"19","value":"ohsu-0070-7-OS-posterior.bmp"},
{"id":"190","key":"190","value":"ohsu-0040-tm-1st-OS-posterior.bmp"},
{"id":"191","key":"191","value":"24_Full.bmp"},
{"id":"192","key":"192","value":"ohsu-0060-2-OD-posterior.bmp"},
{"id":"193","key":"193","value":"ohsu-0049-12-od.bmp"},
{"id":"194","key":"194","value":"ohsu-0031-cc-3rd-OS-posterior.bmp"},
{"id":"195","key":"195","value":"ohsu-0066-kg-5th-OS-posterior.bmp"},
{"id":"196","key":"196","value":"ohsu-0011-mb-1st-OD-posterior.bmp"},
{"id":"197","key":"197","value":"ohsu-0078-1-OS-posterior.bmp"},
{"id":"198","key":"198","value":"ohsu-0119-1-OD-posterior.bmp"},
{"id":"199","key":"199","value":"rcor-0005-1-os.bmp"},
{"id":"2","key":"2","value":"4_full.jpg"},
{"id":"20","key":"20","value":"ohsu-0034-8-od-posterior2.bmp"},
{"id":"200","key":"200","value":"miam-0014-3-os.BMP"},
{"id":"201","key":"201","value":"ohsu-0041-am-1st-OS-posterior.bmp"},
{"id":"202","key":"202","value":"ohsu-0046-vv-1st-OS-posterior.bmp"},
{"id":"203","key":"203","value":"ohsu-0070-7-OS-posterior.bmp"},
{"id":"204","key":"204","value":"ohsu-0083-2-OD-posterior.bmp"},
{"id":"205","key":"205","value":"ohsu-0063-3-OS-posterior.bmp"},
{"id":"206","key":"206","value":"ohsu-0044-5-OS-posterior2.bmp"},
{"id":"207","key":"207","value":"miam-0018-5-od.BMP"},
{"id":"208","key":"208","value":"ohsu-0082-2-OS-posterior.bmp"},
{"id":"209","key":"209","value":"ohsu-0083-2-OS-posterior.bmp"},
{"id":"21","key":"21","value":"ohsu-0046-vv-2nd-OD-posterior.bmp"},
{"id":"210","key":"210","value":"ohsu-0124-6-OS-posterior.bmp"},
{"id":"211","key":"211","value":"5_Full.JPG"},
{"id":"212","key":"212","value":"miam-0011-2-od.BMP"},
{"id":"213","key":"213","value":"ohsu-0065-1-OD-posterior.bmp"},
{"id":"214","key":"214","value":"ohsu-0058-hv-5-OD-posterior2.bmp"},
{"id":"215","key":"215","value":"ohsu-0010-cm-3rd session-OD-posterior2.bmp"},
{"id":"216","key":"216","value":"21_Full.bmp"},
{"id":"217","key":"217","value":"ohsu-0041-am-1st-OD-posterior.bmp"},
{"id":"218","key":"218","value":"ohsu-0054-4-os.bmp"},
{"id":"219","key":"219","value":"ohsu-0038-eh-1st-OD-posterior.bmp"},
{"id":"22","key":"22","value":"32_Full.JPG"},
{"id":"220","key":"220","value":"ohsu-0034-8-od-posterior2.bmp"},
{"id":"221","key":"221","value":"49_ohsu-0020-gl-5th-OD-posterior.bmp"},
{"id":"222","key":"222","value":"81_ohsu-0063-2-OD-posterior.bmp"},
{"id":"223","key":"223","value":"25_corn-0018-3-od-posterior.bmp"},
{"id":"224","key":"224","value":"33_ohsu-001-gb-6th-session-OD-posterior1.bmp"},
{"id":"225","key":"225","value":"57_ohsu-0021-cl-2nd-OD-posterior.bmp"},
{"id":"226","key":"226","value":"85_ohsu-0011-mb-2nd-OS-posterior.bmp"},
{"id":"227","key":"227","value":"89_ohsu-0029-ps-2nd-OD-posterior.bmp"},
{"id":"228","key":"228","value":"65_ohsu-0060-3-OS-posterior.bmp"},
{"id":"229","key":"229","value":"41_beau-0061-4-OS-posterior.bmp"},
{"id":"23","key":"23","value":"miam-0018-4-os.BMP"},
{"id":"230","key":"230","value":"77_ohsu-0030-ks-3rd-OS-posterior.bmp"},
{"id":"231","key":"231","value":"69_ohsu-0063-3-OS-posterior.bmp"},
{"id":"232","key":"232","value":"53_ohsu-0041-am-1st-OD-posterior.bmp"},
{"id":"233","key":"233","value":"1_24-second-OS-temporal.bmp"},
{"id":"234","key":"234","value":"93_ohsu-0072-2-OD-posterior.bmp"},
{"id":"235","key":"235","value":"37_miam-0018-4-os.BMP"},
{"id":"236","key":"236","value":"17_ohsu-0049-nv-14-OS-posterior2.bmp"},
{"id":"237","key":"237","value":"9_miam-0014-3-os.BMP"},
{"id":"238","key":"238","value":"73_ohsu-0031-cc-3rd-OS-posterior.bmp"},
{"id":"239","key":"239","value":"13_4_Full.JPG"},
{"id":"24","key":"24","value":"ohsu-0017-nh-2nd-OD-posterior2.bmp"},
{"id":"240","key":"240","value":"5_ohsu-0054-5-os.bmp"},
{"id":"241","key":"241","value":"61_miam--0027-2-od.BMP"},
{"id":"242","key":"242","value":"29_miam-0018-5-od.BMP"},
{"id":"243","key":"243","value":"97_ohsu-0011-mb-1st-OD-posterior.bmp"},
{"id":"244","key":"244","value":"21_ohsu-0124-6-OS-posterior.bmp"},
{"id":"245","key":"245","value":"45_ohsu-0001-6-os-posterior2.bmp"},
{"id":"25","key":"25","value":"ohsu-0001-6-os-posterior2.bmp"},
{"id":"26","key":"26","value":"corn-0018-3-od-posterior.bmp"},
{"id":"27","key":"27","value":"RCOL-0024-second-OD-posterior.bmp"},
{"id":"28","key":"28","value":"ohsu-0029-ps-2nd-OD-posterior.bmp"},
{"id":"29","key":"29","value":"30_Full.TIF"},
{"id":"3","key":"3","value":"ohsu-0057-5-os.bmp"},
{"id":"30","key":"30","value":"ohsu-0039-xm-1st-OD-posterior.bmp"},
{"id":"31","key":"31","value":"33_Full.JPG"},
{"id":"32","key":"32","value":"ohsu-0060-3-OS-posterior.bmp"},
{"id":"33","key":"33","value":"ohsu-0049-10-os.bmp"},
{"id":"34","key":"34","value":"ohsu-0032-jv-3rd-OD-posterior.bmp"},
{"id":"35","key":"35","value":"ohsu-0002-2-od-posterior2.bmp"},
{"id":"36","key":"36","value":"ohsu-0065-1-OS-posterior.bmp"},
{"id":"37","key":"37","value":"ohsu-0008-jf-3rd session-OS-posterior2.bmp"},
{"id":"38","key":"38","value":"ohsu-0124-6-OD-posterior.bmp"},
{"id":"39","key":"39","value":"ohsu-0096-1-OS-posterior.bmp"},
{"id":"4","key":"4","value":"ohsu-0118-10-OD-posterior.bmp"},
{"id":"40","key":"40","value":"ohsu-0038-eh-2nd-OD-posterior.bmp"},
{"id":"41","key":"41","value":"ohsu-0057-5-os.bmp"},
{"id":"42","key":"42","value":"ohsu-0054-5-os.bmp"},
{"id":"43","key":"43","value":"ohsu-0049-nv-14-OS-posterior2.bmp"},
{"id":"44","key":"44","value":"ohsu-0079-3-OS-posterior.bmp"},
{"id":"45","key":"45","value":"corn-0018-3-os-posterior.bmp"},
{"id":"46","key":"46","value":"ohsu-0118-10-OD-posterior.bmp"},
{"id":"47","key":"47","value":"ohsu-0123-4-OS-posterior.bmp"},
{"id":"48","key":"48","value":"ohsu-0135-7-OS-posterior.bmp"},
{"id":"49","key":"49","value":"8_Full.JPG"},
{"id":"5","key":"5","value":"ohsu-0123-4-OS-posterior.bmp"},
{"id":"50","key":"50","value":"ohsu-0020-gl-5th-OD-posterior.bmp"},
{"id":"51","key":"51","value":"ohsu-0015-cw-1st-OS-posterior.bmp"},
{"id":"52","key":"52","value":"21_Full.TIF"},
{"id":"53","key":"53","value":"miam-0001-2-os.BMP"},
{"id":"54","key":"54","value":"13_Full.JPG"},
{"id":"55","key":"55","value":"ohsu-0063-1-OS-posterior.bmp"},
{"id":"56","key":"56","value":"ohsu-0053-js-2nd-OS-posterior.bmp"},
{"id":"57","key":"57","value":"ohsu-0076-6-OD-posterior.bmp"},
{"id":"58","key":"58","value":"ohsu-0084-7-OS-posterior.bmp"},
{"id":"59","key":"59","value":"ohsu-0085-2-OD-posterior.bmp"},
{"id":"6","key":"6","value":"ohsu-0084-7-OS-posterior.bmp"},
{"id":"60","key":"60","value":"miam-0012-2-od.BMP"},
{"id":"61","key":"61","value":"ohsu-0011-mb-2nd-OS-posterior.bmp"},
{"id":"62","key":"62","value":"ohsu-0040-tm-1st-OD-posterior.bmp"},
{"id":"63","key":"63","value":"ohsu-001-gb-6th session-OD-posterior1.bmp"},
{"id":"64","key":"64","value":"ohsu-0002-3-os-posterior2.bmp"},
{"id":"65","key":"65","value":"miam--0027-2-od.BMP"},
{"id":"66","key":"66","value":"beau-0008-1-OS-posterior.bmp"},
{"id":"67","key":"67","value":"ohsu-0103-2-OS-posterior.bmp"},
{"id":"68","key":"68","value":"beau-0061-4-OS-posterior.bmp"},
{"id":"69","key":"69","value":"ohsu-0104-8-OS-posterior.bmp"},
{"id":"7","key":"7","value":"ohsu-0085-2-OD-posterior.bmp"},
{"id":"70","key":"70","value":"ohsu-0109-1-OD-posterior.bmp"},
{"id":"71","key":"71","value":"ohsu-0087-4-OS-posterior.bmp"},
{"id":"72","key":"72","value":"ohsu-0021-cl-2nd-OD-posterior.bmp"},
{"id":"73","key":"73","value":"corn-0025-2-os.bmp"},
{"id":"74","key":"74","value":"ohsu-0001-4-od-posterior2.bmp"},
{"id":"75","key":"75","value":"ohsu-0043-aw-6th-OS-posterior.bmp"},
{"id":"76","key":"76","value":"ohsu-0006-sr-2nd session-OS-posterior.bmp"},
{"id":"77","key":"77","value":"ohsu-0063-2-OD-posterior.bmp"},
{"id":"78","key":"78","value":"ohsu-0039-xm-2nd-OS-posterior.bmp"},
{"id":"79","key":"79","value":"ohsu-0072-2-OS-posterior.bmp"},
{"id":"8","key":"8","value":"ohsu-0117-1-OD-posterior.bmp"},
{"id":"80","key":"80","value":"ohsu-0072-2-OD-posterior.bmp"},
{"id":"81","key":"81","value":"ohsu-0058-hv-5-OS-posterior2.bmp"},
{"id":"82","key":"82","value":"RCOL-0024-second-OS-posterior.bmp"},
{"id":"83","key":"83","value":"4_Full.JPG"},
{"id":"84","key":"84","value":"ohsu-0117-1-OD-posterior.bmp"},
{"id":"85","key":"85","value":"ohsu-0030-ks-3rd-OS-posterior.bmp"},
{"id":"86","key":"86","value":"OHSU-0024-em-1st-OS-posterior.bmp"},
{"id":"87","key":"87","value":"ohsu-0058-5-OD-posterior.bmp"},
{"id":"88","key":"88","value":"24-second-OS-temporal.bmp"},
{"id":"89","key":"89","value":"ohsu-0073-2-OS-posterior.bmp"},
{"id":"9","key":"9","value":"ohsu-0049-12-od.bmp"},
{"id":"90","key":"90","value":"ohsu-0073-1-OD-posterior.bmp"},
{"id":"91","key":"91","value":"ohsu-0040-tm-1st-OS-posterior.bmp"},
{"id":"92","key":"92","value":"ohsu-0060-2-OD-posterior.bmp"},
{"id":"93","key":"93","value":"ohsu-0049-12-od.bmp"},
{"id":"94","key":"94","value":"ohsu-0031-cc-3rd-OS-posterior.bmp"},
{"id":"95","key":"95","value":"ohsu-0066-kg-5th-OS-posterior.bmp"},
{"id":"96","key":"96","value":"ohsu-0011-mb-1st-OD-posterior.bmp"},
{"id":"97","key":"97","value":"ohsu-0078-1-OS-posterior.bmp"},
{"id":"98","key":"98","value":"ohsu-0119-1-OD-posterior.bmp"},
{"id":"99","key":"99","value":"rcor-0005-1-os.bmp"}
]}
